ZYNacos/__init__.py
ZYNacos/nacos.py
ZYNacos-0.0.5.dist-info/METADATA
ZYNacos-0.0.5.dist-info/WHEEL
ZYNacos-0.0.5.dist-info/top_level.txt
ZYNacos-0.0.5.dist-info/RECORD
