Metadata-Version: 2.1
Name: ZYNacos
Version: 0.0.5
Summary: nacos python zy30651自用
Home-page: https://github.com/zy30651/python-nacos
Author: zy30651
Author-email: zy30651@qq.com
License: apache 3.0
